{"name":"kick","fps":30,"height":520,"groundY":343,"frameCount":180,"frames":[{"rootY":0,"hips":[0,0],"chest":[0.6,-87.6],"neck":[0.6,-87.6],"head":[0.4,-152.5],"shR":[-58.7,-112.6],"elR":[-171.2,-96.8],"haR":[-238.3,-87.4],"shL":[65.5,-107.1],"elL":[168.9,-92.6],"haL":[234.9,-83.3],"hipR":[-23.1,36.4],"knR":[-20.5,186.4],"ftR":[-17.8,340.7],"hipL":[27.2,36.4],"knL":[24.7,179.8],"ftL":[21.8,343.2]},{"rootY":0.1,"hips":[0,0],"chest":[6.9,-87.5],"neck":[6.9,-87.5],"head":[13.3,-152.4],"shR":[-32.2,-108.8],"elR":[-33.7,4.3],"haR":[-63.2,64.9],"shL":[62.6,-110.4],"elL":[70.1,-6.5],"haL":[57,52.4],"hipR":[-31,34.6],"knR":[-64.3,179.9],"ftR":[-51.8,320.6],"hipL":[8.7,38.3],"knL":[-5,180.7],"ftL":[38.3,325.2]},{"rootY":0.1,"hips":[0,0],"chest":[6.9,-87.5],"neck":[6.9,-87.5],"head":[13.5,-152.4],"shR":[-32.3,-108.7],"elR":[-34.3,4.5],"haR":[-64.3,64.9],"shL":[62.7,-110.4],"elL":[70,-6.6],"haL":[56.9,52.5],"hipR":[-30.9,34.6],"knR":[-64.5,180],"ftR":[-52.1,320.6],"hipL":[8.7,38.3],"knL":[-5.2,180.6],"ftL":[38,325.1]},{"rootY":0.2,"hips":[0,0],"chest":[7.1,-87.5],"neck":[7.1,-87.5],"head":[14,-152.3],"shR":[-32.2,-108.8],"elR":[-34.8,4.4],"haR":[-65,64.8],"shL":[62.9,-110.4],"elL":[69.8,-6.5],"haL":[56.9,52.7],"hipR":[-30.9,34.7],"knR":[-64.5,180],"ftR":[-52.2,320.5],"hipL":[8.9,38.2],"knL":[-5,180.6],"ftL":[37.9,325]},{"rootY":0.3,"hips":[0,0],"chest":[7.1,-87.5],"neck":[7.1,-87.5],"head":[14.2,-152.3],"shR":[-32.6,-108.6],"elR":[-35.2,4.6],"haR":[-65.6,64.7],"shL":[63.1,-110.5],"elL":[69.8,-6.6],"haL":[57,52.7],"hipR":[-30.8,34.8],"knR":[-64.6,180],"ftR":[-52.4,320.5],"hipL":[9,38.2],"knL":[-5,180.5],"ftL":[37.8,324.9]},{"rootY":0.2,"hips":[0,0],"chest":[7.2,-87.5],"neck":[7.2,-87.5],"head":[14.5,-152.3],"shR":[-32.7,-108.6],"elR":[-35.2,4.5],"haR":[-65.6,64.6],"shL":[63.3,-110.5],"elL":[69.9,-6.5],"haL":[57.3,53],"hipR":[-30.7,34.8],"knR":[-64.4,180.1],"ftR":[-52.4,320.4],"hipL":[9.3,38.1],"knL":[-4.8,180.5],"ftL":[37.7,325]},{"rootY":0.2,"hips":[0,0],"chest":[7.2,-87.5],"neck":[7.2,-87.5],"head":[14.5,-152.3],"shR":[-32.8,-108.7],"elR":[-35.1,4.5],"haR":[-65.5,64.4],"shL":[63.5,-110.4],"elL":[69.6,-6.4],"haL":[57.3,53.2],"hipR":[-30.8,34.8],"knR":[-64.1,180.2],"ftR":[-52.4,320.5],"hipL":[9.5,38.2],"knL":[-4.5,180.5],"ftL":[37.6,325]},{"rootY":0.3,"hips":[0,0],"chest":[7.3,-87.5],"neck":[7.3,-87.5],"head":[14.9,-152.2],"shR":[-33.6,-109.3],"elR":[-35.7,3.8],"haR":[-65.9,63.8],"shL":[64.3,-109.9],"elL":[70.1,-5.9],"haL":[58,53.8],"hipR":[-30.7,34.9],"knR":[-63.9,180.3],"ftR":[-52.4,320.4],"hipL":[9.7,38.1],"knL":[-4.3,180.4],"ftL":[37.6,325]},{"rootY":0.3,"hips":[0,0],"chest":[7.2,-87.5],"neck":[7.2,-87.5],"head":[15.1,-152.2],"shR":[-34.1,-109.7],"elR":[-36.1,3.5],"haR":[-65.9,63.6],"shL":[64.5,-109.5],"elL":[70.1,-5.5],"haL":[58.5,54.3],"hipR":[-30.9,34.7],"knR":[-63.8,180.2],"ftR":[-52.5,320.3],"hipL":[9.7,38.1],"knL":[-4.2,180.4],"ftL":[37.3,325]},{"rootY":0.3,"hips":[0,0],"chest":[7.4,-87.5],"neck":[7.4,-87.5],"head":[15.4,-152.2],"shR":[-34.3,-109.6],"elR":[-35.9,3.7],"haR":[-65.3,63.8],"shL":[64.9,-109.6],"elL":[70.6,-5.6],"haL":[59.1,54.4],"hipR":[-31,34.7],"knR":[-63.8,180.2],"ftR":[-52.4,320.4],"hipL":[9.7,38.2],"knL":[-4.2,180.4],"ftL":[37.4,325]},{"rootY":0.4,"hips":[0,0],"chest":[7.4,-87.5],"neck":[7.4,-87.5],"head":[15.8,-152.1],"shR":[-34.6,-109.6],"elR":[-35.9,3.7],"haR":[-65,64],"shL":[65.2,-109.6],"elL":[70.8,-5.5],"haL":[59.4,54.5],"hipR":[-31.1,34.5],"knR":[-63.9,180.1],"ftR":[-52.4,320.3],"hipL":[9.6,38.2],"knL":[-4.3,180.5],"ftL":[37.4,324.9]},{"rootY":0.4,"hips":[0,0],"chest":[7.5,-87.5],"neck":[7.5,-87.5],"head":[16,-152.1],"shR":[-34.6,-109.5],"elR":[-35.5,3.8],"haR":[-64.3,64.1],"shL":[65.4,-109.6],"elL":[71.1,-5.5],"haL":[60.4,55.2],"hipR":[-31.2,34.4],"knR":[-63.8,180.1],"ftR":[-52.3,320.3],"hipL":[9.5,38.3],"knL":[-4.3,180.6],"ftL":[37.3,324.9]},{"rootY":0.3,"hips":[0,0],"chest":[7.5,-87.5],"neck":[7.5,-87.5],"head":[16.1,-152.1],"shR":[-35.1,-109.3],"elR":[-35.7,4.1],"haR":[-64.1,64.5],"shL":[65.8,-109.7],"elL":[71.4,-5.6],"haL":[60.6,54.8],"hipR":[-31.3,34.4],"knR":[-63.7,180],"ftR":[-52.3,320.3],"hipL":[9.6,38.4],"knL":[-4.3,180.6],"ftL":[37.4,325]},{"rootY":0.4,"hips":[0,0],"chest":[7.7,-87.5],"neck":[7.7,-87.5],"head":[16.3,-152.1],"shR":[-34.8,-109.6],"elR":[-35.3,3.8],"haR":[-63.5,64.2],"shL":[65.8,-109.5],"elL":[71.4,-5.3],"haL":[60.8,55.2],"hipR":[-31.3,34.4],"knR":[-63.6,180.1],"ftR":[-52.2,320.2],"hipL":[9.7,38.3],"knL":[-4,180.6],"ftL":[37.4,325]},{"rootY":0.3,"hips":[0,0],"chest":[7.8,-87.4],"neck":[7.8,-87.4],"head":[17,-152],"shR":[-34.8,-109.7],"elR":[-35.1,3.8],"haR":[-63.2,64],"shL":[66.2,-109.4],"elL":[71.7,-5.2],"haL":[61.1,55.3],"hipR":[-31.1,34.6],"knR":[-63.5,180.2],"ftR":[-52.1,320.3],"hipL":[10,38.2],"knL":[-3.7,180.5],"ftL":[37.5,325]},{"rootY":0.4,"hips":[0,0],"chest":[7.9,-87.4],"neck":[7.9,-87.4],"head":[17.2,-152],"shR":[-34.9,-109.6],"elR":[-35,3.9],"haR":[-62.9,64],"shL":[66.4,-109.4],"elL":[71.7,-5.2],"haL":[61.3,55.5],"hipR":[-31,34.7],"knR":[-63.3,180.3],"ftR":[-51.9,320.3],"hipL":[10.3,38.1],"knL":[-3.2,180.3],"ftL":[37.7,325]},{"rootY":0.4,"hips":[0,0],"chest":[8,-87.4],"neck":[8,-87.4],"head":[17.4,-152],"shR":[-35,-109.7],"elR":[-35.2,3.8],"haR":[-63,63.9],"shL":[66.6,-109.2],"elL":[71.5,-5],"haL":[61.4,55.7],"hipR":[-31,34.6],"knR":[-63.4,180.3],"ftR":[-51.9,320.2],"hipL":[10.4,38],"knL":[-2.9,180.3],"ftL":[37.8,324.9]},{"rootY":0.4,"hips":[0,0],"chest":[7.9,-87.4],"neck":[7.9,-87.4],"head":[17.4,-152],"shR":[-35.2,-109.9],"elR":[-35.5,3.6],"haR":[-63.3,63.7],"shL":[66.8,-109.1],"elL":[71.6,-4.8],"haL":[61.4,55.7],"hipR":[-31,34.6],"knR":[-63.3,180.3],"ftR":[-51.8,320.2],"hipL":[10.4,38.1],"knL":[-2.9,180.4],"ftL":[37.9,325]},{"rootY":0.4,"hips":[0,0],"chest":[7.7,-87.5],"neck":[7.7,-87.5],"head":[17.3,-152],"shR":[-35.8,-109.4],"elR":[-36.3,4.1],"haR":[-64,64.2],"shL":[67,-109.2],"elL":[71.6,-5],"haL":[62.7,56.6],"hipR":[-30.9,34.7],"knR":[-63.1,180.4],"ftR":[-51.8,320.3],"hipL":[10.8,38.1],"knL":[-2.6,180.4],"ftL":[38,325.1]},{"rootY":0.5,"hips":[0,0],"chest":[7.7,-87.5],"neck":[7.7,-87.5],"head":[17.5,-151.9],"shR":[-36.3,-110.1],"elR":[-37,3.4],"haR":[-64.7,63.4],"shL":[67.3,-108.9],"elL":[71.6,-4.6],"haL":[62.7,57],"hipR":[-31,34.6],"knR":[-62.9,180.4],"ftR":[-51.7,320.1],"hipL":[11,38.1],"knL":[-1.9,180.4],"ftL":[38.1,325.1]},{"rootY":0.4,"hips":[0,0],"chest":[7.8,-87.5],"neck":[7.8,-87.5],"head":[17.6,-151.9],"shR":[-36.4,-110.1],"elR":[-37.6,3.4],"haR":[-65.2,63.6],"shL":[67.4,-108.8],"elL":[71.4,-4.6],"haL":[62.4,56.7],"hipR":[-30.9,34.7],"knR":[-62.5,180.6],"ftR":[-51.5,320.1],"hipL":[11.5,38.1],"knL":[-1.4,180.3],"ftL":[38.2,325.2]},{"rootY":0.3,"hips":[0,0],"chest":[7.8,-87.5],"neck":[7.8,-87.5],"head":[17.8,-151.9],"shR":[-36.7,-110],"elR":[-38,3.4],"haR":[-65.6,63.6],"shL":[67.6,-108.9],"elL":[71.6,-4.6],"haL":[62.5,56.4],"hipR":[-30.8,34.8],"knR":[-62,180.8],"ftR":[-51.3,320.2],"hipL":[12,38.1],"knL":[-0.4,180.3],"ftL":[38.4,325.4]},{"rootY":0.3,"hips":[0,0],"chest":[7.7,-87.5],"neck":[7.7,-87.5],"head":[17.8,-151.9],"shR":[-37.4,-110.2],"elR":[-39,3.2],"haR":[-66.4,63.6],"shL":[67.9,-108.7],"elL":[72,-4.4],"haL":[62.9,56.4],"hipR":[-30.9,34.7],"knR":[-61.8,180.8],"ftR":[-51.1,320],"hipL":[12.1,38.1],"knL":[0,180.4],"ftL":[38.4,325.4]},{"rootY":0.3,"hips":[0,0],"chest":[7.6,-87.5],"neck":[7.6,-87.5],"head":[17.4,-151.9],"shR":[-38,-110.3],"elR":[-39.8,3.1],"haR":[-66.8,63.6],"shL":[68.2,-108.7],"elL":[72.5,-4.4],"haL":[63.2,56.2],"hipR":[-31,34.5],"knR":[-61.2,180.7],"ftR":[-50.8,320.1],"hipL":[12.1,38.3],"knL":[0.3,180.5],"ftL":[38.6,325.6]},{"rootY":0.2,"hips":[0,0],"chest":[7.7,-87.5],"neck":[7.7,-87.5],"head":[17.8,-151.9],"shR":[-39,-110.8],"elR":[-41,2.6],"haR":[-67.9,63.3],"shL":[69,-108.4],"elL":[73.4,-4.1],"haL":[64,56.2],"hipR":[-30.9,34.7],"knR":[-60.7,180.9],"ftR":[-50.5,320.2],"hipL":[12.5,38.3],"knL":[0.7,180.5],"ftL":[38.8,325.6]},{"rootY":0.1,"hips":[0,0],"chest":[7.5,-87.5],"neck":[7.5,-87.5],"head":[17.7,-152],"shR":[-39.6,-110.7],"elR":[-41.6,2.6],"haR":[-68.3,63.4],"shL":[69.1,-108.4],"elL":[74,-4.2],"haL":[64.6,55.9],"hipR":[-30.9,34.6],"knR":[-60.1,181],"ftR":[-50.1,320.2],"hipL":[12.8,38.4],"knL":[1.4,180.5],"ftL":[39.2,325.7]},{"rootY":0,"hips":[0,0],"chest":[7.4,-87.5],"neck":[7.4,-87.5],"head":[17.6,-152],"shR":[-40.5,-110.7],"elR":[-42.7,2.7],"haR":[-69.2,63.5],"shL":[69.3,-108.5],"elL":[74.7,-4.3],"haL":[65.4,55.6],"hipR":[-31,34.6],"knR":[-59.5,181.1],"ftR":[-49.7,320.2],"hipL":[13,38.5],"knL":[1.9,180.6],"ftL":[39.4,325.9]},{"rootY":0.1,"hips":[0,0],"chest":[7.3,-87.5],"neck":[7.3,-87.5],"head":[17.4,-152.1],"shR":[-41.3,-110.7],"elR":[-43.8,2.5],"haR":[-70.4,63.4],"shL":[69.5,-108.5],"elL":[75.4,-4.3],"haL":[66.7,55.3],"hipR":[-30.8,34.7],"knR":[-59.1,181.3],"ftR":[-49.3,320.3],"hipL":[13.5,38.3],"knL":[2.4,180.4],"ftL":[39.8,325.8]},{"rootY":0,"hips":[0,0],"chest":[7.1,-87.5],"neck":[7.1,-87.5],"head":[17.1,-152.2],"shR":[-42,-110.6],"elR":[-44.3,2.6],"haR":[-71.3,63.2],"shL":[69.5,-108.7],"elL":[76.5,-4.6],"haL":[68.5,54.8],"hipR":[-30.5,34.9],"knR":[-58.7,181.5],"ftR":[-49,320.4],"hipL":[14,38.2],"knL":[3.3,180.3],"ftL":[40,325.8]},{"rootY":0,"hips":[0,0],"chest":[6.8,-87.5],"neck":[6.8,-87.5],"head":[16.8,-152.2],"shR":[-42.9,-110.4],"elR":[-45.2,2.7],"haR":[-73,62.9],"shL":[69.5,-108.9],"elL":[78.2,-4.9],"haL":[71,54.1],"hipR":[-30.5,34.9],"knR":[-58.2,181.6],"ftR":[-48.5,320.3],"hipL":[14.2,38.2],"knL":[3.8,180.3],"ftL":[40.3,325.8]},{"rootY":0,"hips":[0,0],"chest":[6.5,-87.6],"neck":[6.5,-87.6],"head":[16.3,-152.3],"shR":[-43.7,-110.1],"elR":[-46.2,2.8],"haR":[-74.9,62.4],"shL":[69.3,-109.2],"elL":[79.9,-5.5],"haL":[74.1,53.2],"hipR":[-30.7,34.7],"knR":[-58.1,181.5],"ftR":[-48.2,320.2],"hipL":[14,38.3],"knL":[4,180.4],"ftL":[40.5,325.9]},{"rootY":0.1,"hips":[0,0],"chest":[6.1,-87.6],"neck":[6.1,-87.6],"head":[15.6,-152.3],"shR":[-44.7,-110.3],"elR":[-47.3,2.5],"haR":[-77.2,61.5],"shL":[69.2,-109.2],"elL":[81.7,-5.7],"haL":[77.4,52.3],"hipR":[-30.7,34.7],"knR":[-57.8,181.5],"ftR":[-47.9,320.1],"hipL":[14.1,38.3],"knL":[4.1,180.4],"ftL":[40.7,325.9]},{"rootY":0,"hips":[0,0],"chest":[5.9,-87.6],"neck":[5.9,-87.6],"head":[15.2,-152.3],"shR":[-45.2,-110.4],"elR":[-48.8,2.4],"haR":[-79.7,60.9],"shL":[69.1,-109.2],"elL":[83.3,-6.1],"haL":[81.2,51.6],"hipR":[-30.7,34.7],"knR":[-57.3,181.5],"ftR":[-47.4,320.2],"hipL":[14.1,38.5],"knL":[4.3,180.4],"ftL":[41.1,325.9]},{"rootY":-0.1,"hips":[0,0],"chest":[5.7,-87.6],"neck":[5.7,-87.6],"head":[14.8,-152.3],"shR":[-45.5,-110],"elR":[-50.4,2.7],"haR":[-82.1,60.8],"shL":[68.8,-109.6],"elL":[84.5,-6.8],"haL":[84.7,50.4],"hipR":[-30.6,34.8],"knR":[-57.3,181.6],"ftR":[-47.2,320.3],"hipL":[14.3,38.4],"knL":[4.7,180.4],"ftL":[41.1,325.8]},{"rootY":0,"hips":[0,0],"chest":[5.6,-87.6],"neck":[5.6,-87.6],"head":[14.3,-152.3],"shR":[-45.9,-109.9],"elR":[-52.1,2.7],"haR":[-84.3,60.7],"shL":[68.7,-109.8],"elL":[85.7,-7.4],"haL":[88.1,49.3],"hipR":[-30.6,34.7],"knR":[-57,181.6],"ftR":[-46.8,320.3],"hipL":[14.3,38.4],"knL":[4.9,180.3],"ftL":[41.2,325.9]},{"rootY":-0.1,"hips":[0,0],"chest":[5.5,-87.6],"neck":[5.5,-87.6],"head":[14,-152.3],"shR":[-46,-109.5],"elR":[-53.9,3.1],"haR":[-86.5,60.9],"shL":[68.3,-110.2],"elL":[85.8,-8.1],"haL":[90.4,48.3],"hipR":[-30.5,34.9],"knR":[-57.8,181.5],"ftR":[-47.1,320.3],"hipL":[14.2,38.3],"knL":[4.2,180.3],"ftL":[41,325.9]},{"rootY":-0.1,"hips":[0,0],"chest":[5.3,-87.6],"neck":[5.3,-87.6],"head":[13.5,-152.3],"shR":[-46.1,-109.3],"elR":[-54.7,3.3],"haR":[-87.7,61],"shL":[68.1,-110.4],"elL":[86.5,-8.5],"haL":[92.6,47.7],"hipR":[-30.5,34.9],"knR":[-58,181.5],"ftR":[-47,320.4],"hipL":[14,38.2],"knL":[3.6,180.2],"ftL":[41.1,325.8]},{"rootY":-0.1,"hips":[0,0],"chest":[4.9,-87.7],"neck":[4.9,-87.7],"head":[12.8,-152.4],"shR":[-46.3,-109.1],"elR":[-55.4,3.6],"haR":[-88.7,61.1],"shL":[67.6,-110.5],"elL":[86.3,-9],"haL":[93.7,47.1],"hipR":[-30.6,34.8],"knR":[-58.3,181.4],"ftR":[-47,320.5],"hipL":[13.7,38.3],"knL":[3.2,180.3],"ftL":[41.1,325.8]},{"rootY":-0.1,"hips":[0,0],"chest":[4.6,-87.7],"neck":[4.6,-87.7],"head":[12.2,-152.4],"shR":[-46.5,-108.7],"elR":[-55.2,4],"haR":[-89.2,61.2],"shL":[67.2,-110.8],"elL":[85.7,-9.5],"haL":[93.9,46.7],"hipR":[-30.5,34.9],"knR":[-59,181.4],"ftR":[-47.3,320.6],"hipL":[13.6,38.2],"knL":[2.8,180.3],"ftL":[40.8,325.6]},{"rootY":-0.2,"hips":[0,0],"chest":[4.5,-87.7],"neck":[4.5,-87.7],"head":[11.7,-152.4],"shR":[-46.1,-108.2],"elR":[-54.3,4.6],"haR":[-88.7,61.2],"shL":[66.6,-111.4],"elL":[85,-10.1],"haL":[93.4,46],"hipR":[-30.6,34.9],"knR":[-59.6,181.2],"ftR":[-47.8,320.7],"hipL":[13,38.3],"knL":[1.7,180.4],"ftL":[40.5,325.7]},{"rootY":-0.3,"hips":[0,0],"chest":[4.2,-87.7],"neck":[4.2,-87.7],"head":[11.1,-152.5],"shR":[-45.7,-107.7],"elR":[-53.4,5.1],"haR":[-88.5,61.3],"shL":[66,-111.6],"elL":[84.4,-10.5],"haL":[92.3,45.7],"hipR":[-30.7,34.8],"knR":[-59.8,181.1],"ftR":[-47.8,320.8],"hipL":[12.7,38.4],"knL":[1.4,180.5],"ftL":[40.6,325.8]},{"rootY":-0.3,"hips":[0,0],"chest":[4,-87.7],"neck":[4,-87.7],"head":[10.8,-152.6],"shR":[-45,-107.7],"elR":[-51.8,5.2],"haR":[-87.8,60.8],"shL":[65.3,-111.7],"elL":[83.4,-10.6],"haL":[90.4,45.6],"hipR":[-30.3,35.2],"knR":[-60.6,181.2],"ftR":[-48.4,321],"hipL":[12.8,38.2],"knL":[1.1,180.3],"ftL":[40.2,325.6]},{"rootY":-0.5,"hips":[0,0],"chest":[4,-87.7],"neck":[4,-87.7],"head":[10.6,-152.6],"shR":[-44.1,-107.5],"elR":[-49.6,5.6],"haR":[-86.3,60.7],"shL":[64.7,-111.9],"elL":[82,-10.8],"haL":[87.9,45.2],"hipR":[-30.3,35.3],"knR":[-61.2,181.1],"ftR":[-48.9,321.3],"hipL":[12.5,38.3],"knL":[0.4,180.3],"ftL":[39.9,325.8]},{"rootY":-0.5,"hips":[0,0],"chest":[3.9,-87.8],"neck":[3.9,-87.8],"head":[10.5,-152.7],"shR":[-42.9,-107.3],"elR":[-47.5,5.8],"haR":[-84.9,60.6],"shL":[63.9,-112],"elL":[80.4,-11],"haL":[84.8,44.7],"hipR":[-30.3,35.3],"knR":[-62.2,180.8],"ftR":[-49.5,321.4],"hipL":[11.7,38.4],"knL":[-1.1,180.5],"ftL":[39.8,325.8]},{"rootY":-0.6,"hips":[0,0],"chest":[4,-87.7],"neck":[4,-87.7],"head":[10.4,-152.8],"shR":[-41.3,-107.3],"elR":[-45.1,5.9],"haR":[-83.1,60.5],"shL":[63.2,-112.1],"elL":[79.1,-11.2],"haL":[81.6,44.2],"hipR":[-30.1,35.4],"knR":[-63.2,180.7],"ftR":[-50.1,321.6],"hipL":[11.2,38.4],"knL":[-2.2,180.5],"ftL":[39.6,325.8]},{"rootY":-0.6,"hips":[0,0],"chest":[4.2,-87.7],"neck":[4.2,-87.7],"head":[10.4,-152.8],"shR":[-39.4,-107.7],"elR":[-42.5,5.5],"haR":[-80.9,60.1],"shL":[62.3,-111.8],"elL":[77,-11],"haL":[77.4,44],"hipR":[-29.9,35.5],"knR":[-64.3,180.5],"ftR":[-51,321.9],"hipL":[10.6,38.3],"knL":[-3.2,180.4],"ftL":[39.4,325.6]},{"rootY":-0.6,"hips":[0,0],"chest":[4.2,-87.7],"neck":[4.2,-87.7],"head":[10.4,-152.9],"shR":[-37.3,-107.4],"elR":[-40,5.8],"haR":[-78.6,60.6],"shL":[60.9,-112],"elL":[74.1,-11.2],"haL":[72.2,43.3],"hipR":[-29.8,35.6],"knR":[-65.4,180.2],"ftR":[-51.6,322],"hipL":[9.8,38.4],"knL":[-4.5,180.5],"ftL":[39.4,325.6]},{"rootY":-0.5,"hips":[0,0],"chest":[4.1,-87.7],"neck":[4.1,-87.7],"head":[10.1,-152.9],"shR":[-34.9,-107],"elR":[-37.3,6.3],"haR":[-75.9,61.3],"shL":[59.2,-112.3],"elL":[70.5,-11.5],"haL":[66.3,42.5],"hipR":[-29.7,35.6],"knR":[-66.6,179.9],"ftR":[-52.5,321.9],"hipL":[8.9,38.4],"knL":[-5.9,180.5],"ftL":[39.2,325.7]},{"rootY":-0.5,"hips":[0,0],"chest":[3.9,-87.7],"neck":[3.9,-87.7],"head":[9.9,-152.9],"shR":[-32.4,-106.6],"elR":[-34.5,6.7],"haR":[-73,62.2],"shL":[57.2,-112.6],"elL":[67.3,-11.6],"haL":[60.3,42.1],"hipR":[-29.4,35.7],"knR":[-67.7,179.7],"ftR":[-53.2,322],"hipL":[8.4,38.3],"knL":[-6.7,180.5],"ftL":[39.1,325.7]},{"rootY":-0.4,"hips":[0,0],"chest":[3.8,-87.7],"neck":[3.8,-87.7],"head":[10,-152.9],"shR":[-31,-107.2],"elR":[-32.8,6],"haR":[-70.8,62],"shL":[55.9,-112.2],"elL":[64.2,-11.2],"haL":[54.3,41.7],"hipR":[-29.2,35.8],"knR":[-68.6,179.4],"ftR":[-53.7,322],"hipL":[7.9,38.3],"knL":[-7.6,180.5],"ftL":[39,325.6]},{"rootY":-0.4,"hips":[0,0],"chest":[3.8,-87.7],"neck":[3.8,-87.7],"head":[10,-152.9],"shR":[-28.5,-107.2],"elR":[-29.8,6.1],"haR":[-67.1,62.7],"shL":[54.2,-112.2],"elL":[61,-11.2],"haL":[48,41.3],"hipR":[-29.2,35.8],"knR":[-68.4,179.4],"ftR":[-53.9,322],"hipL":[7.4,38.3],"knL":[-8.3,180.5],"ftL":[39.1,325.6]},{"rootY":-0.2,"hips":[0,0],"chest":[4.1,-87.7],"neck":[4.1,-87.7],"head":[10.4,-152.8],"shR":[-26.1,-107],"elR":[-26.5,6.2],"haR":[-63,63.2],"shL":[52.8,-112.2],"elL":[58.3,-11.2],"haL":[42.3,40.8],"hipR":[-29.1,35.8],"knR":[-68.4,179.4],"ftR":[-53.8,322],"hipL":[7,38.2],"knL":[-8.5,180.5],"ftL":[39.1,325.3]},{"rootY":0,"hips":[0,0],"chest":[4,-87.7],"neck":[4,-87.7],"head":[10.2,-152.9],"shR":[-24.2,-106.8],"elR":[-23.3,6.3],"haR":[-58.8,63.8],"shL":[51.3,-112.4],"elL":[55.2,-11.4],"haL":[36.3,39.5],"hipR":[-29.1,35.8],"knR":[-68.8,179.2],"ftR":[-54.1,321.7],"hipL":[6.7,38],"knL":[-9,180.3],"ftL":[39,325.1]},{"rootY":0.2,"hips":[0,0],"chest":[4.2,-87.6],"neck":[4.2,-87.6],"head":[10.3,-152.8],"shR":[-22.3,-106.6],"elR":[-19.6,6.3],"haR":[-54.2,64.2],"shL":[49.8,-112.7],"elL":[52.2,-11.6],"haL":[30.6,38.4],"hipR":[-29.2,35.7],"knR":[-68.9,179.1],"ftR":[-54.2,321.5],"hipL":[6.3,38],"knL":[-9.5,180.3],"ftL":[38.9,324.9]},{"rootY":0.3,"hips":[0,0],"chest":[4,-87.6],"neck":[4,-87.6],"head":[9.8,-152.9],"shR":[-21.4,-106.5],"elR":[-17.3,6.2],"haR":[-51.3,64.2],"shL":[48.5,-112.9],"elL":[49.7,-11.8],"haL":[25.7,37.3],"hipR":[-29.9,35],"knR":[-68.9,178.6],"ftR":[-54.3,321],"hipL":[5.4,38.4],"knL":[-10.5,180.7],"ftL":[38.8,324.9]},{"rootY":0.5,"hips":[0,0],"chest":[4.8,-87.6],"neck":[4.8,-87.6],"head":[10,-152.8],"shR":[-19.1,-106.2],"elR":[-14.5,6.5],"haR":[-47.2,64.7],"shL":[48.2,-113],"elL":[48.6,-11.6],"haL":[22.9,36.9],"hipR":[-29.2,35.7],"knR":[-69.2,179],"ftR":[-54.2,321],"hipL":[6.1,37.7],"knL":[-9.3,180.1],"ftL":[38.9,324.6]},{"rootY":0.7,"hips":[0,0],"chest":[5,-87.6],"neck":[5,-87.6],"head":[10,-152.9],"shR":[-18.4,-106.5],"elR":[-13.7,6],"haR":[-45.5,64.4],"shL":[48.1,-112.7],"elL":[48,-12.2],"haL":[20.3,35.2],"hipR":[-29.3,35.6],"knR":[-69.1,179],"ftR":[-54.1,320.9],"hipL":[5.8,37.8],"knL":[-9.5,180.2],"ftL":[38.9,324.5]},{"rootY":0.6,"hips":[0,0],"chest":[5.3,-87.5],"neck":[5.3,-87.5],"head":[9.5,-152.9],"shR":[-17.9,-106.8],"elR":[-13.3,5.6],"haR":[-44.8,63.9],"shL":[48.2,-112.4],"elL":[47.6,-11.3],"haL":[19.5,35.8],"hipR":[-29.3,35.6],"knR":[-68.9,179],"ftR":[-53.9,320.9],"hipL":[5.7,37.8],"knL":[-9.5,180.3],"ftL":[39,324.5]},{"rootY":0.7,"hips":[0,0],"chest":[5.7,-87.5],"neck":[5.7,-87.5],"head":[9.7,-152.8],"shR":[-17.3,-106.9],"elR":[-13.4,5.5],"haR":[-44.9,63.5],"shL":[48.4,-112.3],"elL":[47.4,-11.6],"haL":[18.8,35],"hipR":[-29,35.9],"knR":[-69.2,179.2],"ftR":[-53.8,320.8],"hipL":[6.1,37.4],"knL":[-8.9,179.9],"ftL":[39,324.4]},{"rootY":0.7,"hips":[0,0],"chest":[6,-87.5],"neck":[6,-87.5],"head":[9.6,-152.8],"shR":[-17.1,-106.9],"elR":[-14.3,5.4],"haR":[-46.4,63],"shL":[48.9,-112.2],"elL":[48.4,-11.2],"haL":[20,35.4],"hipR":[-28.9,36],"knR":[-69.3,179.3],"ftR":[-53.7,320.7],"hipL":[6.4,37.3],"knL":[-8.3,179.8],"ftL":[39.2,324.3]},{"rootY":0.7,"hips":[0,0],"chest":[6.2,-87.5],"neck":[6.2,-87.5],"head":[9.7,-152.7],"shR":[-17.5,-107.1],"elR":[-15.9,5.1],"haR":[-49.2,62.1],"shL":[49.4,-112.1],"elL":[49.8,-10.8],"haL":[22.3,35.9],"hipR":[-29.2,35.8],"knR":[-68.9,179.2],"ftR":[-53.2,320.6],"hipL":[6.1,37.5],"knL":[-8.4,180],"ftL":[39.6,324.3]},{"rootY":0.6,"hips":[0,0],"chest":[6.3,-87.5],"neck":[6.3,-87.5],"head":[10,-152.7],"shR":[-18.6,-107.3],"elR":[-18.3,4.8],"haR":[-53.1,61],"shL":[50.6,-111.8],"elL":[51.2,-10.8],"haL":[25.2,36.4],"hipR":[-29.6,35.5],"knR":[-68.3,179.2],"ftR":[-52.9,320.8],"hipL":[6.1,37.8],"knL":[-8.6,180.3],"ftL":[39.7,324.4]},{"rootY":0.5,"hips":[0,0],"chest":[6.3,-87.4],"neck":[6.3,-87.4],"head":[9.9,-152.7],"shR":[-20,-107.5],"elR":[-20.9,4.3],"haR":[-57.7,59.7],"shL":[51.8,-111.5],"elL":[53.4,-10.5],"haL":[29.1,37.2],"hipR":[-30,35.1],"knR":[-67.2,179.1],"ftR":[-52.4,320.7],"hipL":[6.2,38.3],"knL":[-8.6,180.7],"ftL":[39.8,324.7]},{"rootY":0.5,"hips":[0,0],"chest":[6.7,-87.4],"neck":[6.7,-87.4],"head":[10.4,-152.7],"shR":[-20.9,-107.8],"elR":[-24.8,4.2],"haR":[-62.9,58.8],"shL":[53.4,-111.2],"elL":[55.9,-10.1],"haL":[33.8,38.2],"hipR":[-30.2,35],"knR":[-67,179.2],"ftR":[-51.9,320.7],"hipL":[6.4,38.2],"knL":[-8,180.6],"ftL":[40.3,324.5]},{"rootY":0.4,"hips":[0,0],"chest":[7.2,-87.4],"neck":[7.2,-87.4],"head":[11.3,-152.6],"shR":[-22.8,-108.4],"elR":[-28.2,3.5],"haR":[-68.3,57.2],"shL":[55.9,-110.6],"elL":[59.3,-9.3],"haL":[39.8,39.6],"hipR":[-30,35.4],"knR":[-65.8,179.7],"ftR":[-51,320.7],"hipL":[7.9,38],"knL":[-5.5,180.4],"ftL":[40.5,324.9]},{"rootY":0.4,"hips":[0,0],"chest":[7.4,-87.4],"neck":[7.4,-87.4],"head":[11.6,-152.6],"shR":[-24.8,-108.7],"elR":[-32.4,3.1],"haR":[-74,56],"shL":[58,-110.2],"elL":[62.2,-8.5],"haL":[45.7,40.7],"hipR":[-30,35.4],"knR":[-65.1,180],"ftR":[-50.6,320.7],"hipL":[8.8,37.9],"knL":[-4.6,180.3],"ftL":[40.7,324.9]},{"rootY":0.4,"hips":[0,0],"chest":[7.7,-87.4],"neck":[7.7,-87.4],"head":[12.2,-152.5],"shR":[-26.7,-108.7],"elR":[-36.5,3],"haR":[-79.5,55.1],"shL":[60,-110.1],"elL":[65,-8.3],"haL":[51.6,41.8],"hipR":[-29.9,35.5],"knR":[-64.1,180.4],"ftR":[-50,320.7],"hipL":[9.7,37.9],"knL":[-3.4,180.3],"ftL":[41,324.9]},{"rootY":0.2,"hips":[0,0],"chest":[8.2,-87.3],"neck":[8.2,-87.3],"head":[12.8,-152.5],"shR":[-27.9,-108.2],"elR":[-39.9,3.5],"haR":[-84.1,54.8],"shL":[62,-110.4],"elL":[67.7,-8.6],"haL":[57.4,42.1],"hipR":[-30.1,35.4],"knR":[-63,180.6],"ftR":[-49.3,320.6],"hipL":[10.3,38],"knL":[-2.3,180.4],"ftL":[41.3,325.1]},{"rootY":0.1,"hips":[0,0],"chest":[8.2,-87.4],"neck":[8.2,-87.4],"head":[13.6,-152.4],"shR":[-31.1,-109.3],"elR":[-45.4,2.3],"haR":[-90.3,53.1],"shL":[64.3,-109.6],"elL":[70.7,-7.5],"haL":[63.5,44],"hipR":[-30.1,35.4],"knR":[-62,180.8],"ftR":[-48.9,320.6],"hipL":[11.3,38.1],"knL":[-1.1,180.3],"ftL":[41.4,325.3]},{"rootY":0.1,"hips":[0,0],"chest":[8.2,-87.4],"neck":[8.2,-87.4],"head":[13.4,-152.5],"shR":[-33.2,-109],"elR":[-49.9,2.4],"haR":[-95.3,52.6],"shL":[65.6,-109.8],"elL":[73.3,-7.2],"haL":[69.2,45],"hipR":[-30.2,35.4],"knR":[-61.1,181],"ftR":[-48.5,320.5],"hipL":[12,38.1],"knL":[-0.2,180.3],"ftL":[41.3,325.3]},{"rootY":0.1,"hips":[0,0],"chest":[8.3,-87.4],"neck":[8.3,-87.4],"head":[13.7,-152.4],"shR":[-35.4,-109.8],"elR":[-54,1.5],"haR":[-99.6,51.1],"shL":[67.4,-109.2],"elL":[76,-6.4],"haL":[74.9,46.4],"hipR":[-29.8,35.6],"knR":[-60.2,181.4],"ftR":[-48.1,320.6],"hipL":[13.2,37.9],"knL":[1.6,180],"ftL":[41.4,325.4]},{"rootY":0.1,"hips":[0,0],"chest":[7.6,-87.5],"neck":[7.6,-87.5],"head":[13.5,-152.4],"shR":[-38.2,-111.2],"elR":[-58.4,0.2],"haR":[-103.9,49.3],"shL":[68.3,-108.1],"elL":[78.4,-5.3],"haL":[80.3,47.8],"hipR":[-30.1,35.3],"knR":[-59.3,181.4],"ftR":[-47.7,320.5],"hipL":[13.6,38.1],"knL":[2.4,180.1],"ftL":[41.4,325.4]},{"rootY":0.1,"hips":[0,0],"chest":[7.4,-87.5],"neck":[7.4,-87.5],"head":[13.9,-152.5],"shR":[-40.7,-110.3],"elR":[-62.2,0.9],"haR":[-107.4,49.2],"shL":[69.3,-108.8],"elL":[80.6,-5.8],"haL":[85.1,47.4],"hipR":[-29.9,35.4],"knR":[-58.2,181.7],"ftR":[-47.3,320.4],"hipL":[14.7,38.1],"knL":[4.1,180],"ftL":[41.4,325.7]},{"rootY":0.1,"hips":[0,0],"chest":[7.2,-87.5],"neck":[7.2,-87.5],"head":[14.2,-152.5],"shR":[-43.3,-109.8],"elR":[-66.1,1.3],"haR":[-110.6,49.2],"shL":[70.1,-109.2],"elL":[82.2,-6.1],"haL":[89.5,47.4],"hipR":[-29.2,35.8],"knR":[-57.5,182.2],"ftR":[-47.3,320.6],"hipL":[16.4,37.7],"knL":[5.8,179.4],"ftL":[41.1,325.6]},{"rootY":0.1,"hips":[0,0],"chest":[7,-87.5],"neck":[7,-87.5],"head":[14.4,-152.5],"shR":[-45.3,-110.5],"elR":[-69.1,0.5],"haR":[-112.7,47.8],"shL":[70.8,-108.9],"elL":[83.6,-5.7],"haL":[93.7,48],"hipR":[-29.7,35.4],"knR":[-55.9,182.1],"ftR":[-46.4,320.3],"hipL":[16.4,38.1],"knL":[6.8,179.7],"ftL":[41.7,325.9]},{"rootY":0,"hips":[0,0],"chest":[6.8,-87.5],"neck":[6.8,-87.5],"head":[14.5,-152.5],"shR":[-47.2,-110.4],"elR":[-71.9,0.4],"haR":[-114.3,47.3],"shL":[71.2,-108.9],"elL":[84.6,-5.8],"haL":[97.4,48.1],"hipR":[-29.7,35.1],"knR":[-54.7,182.1],"ftR":[-46,320.4],"hipL":[17,38.3],"knL":[8,179.7],"ftL":[42.2,326.3]},{"rootY":-0.2,"hips":[0,0],"chest":[6.7,-87.6],"neck":[6.7,-87.6],"head":[14.2,-152.5],"shR":[-48.6,-110.6],"elR":[-74,0.1],"haR":[-115.3,46.7],"shL":[71.6,-108.9],"elL":[85.5,-5.7],"haL":[100.6,48.3],"hipR":[-29.6,35.1],"knR":[-53.1,182.4],"ftR":[-45.2,320.4],"hipL":[17.9,38.5],"knL":[9.9,179.7],"ftL":[42.5,326.5]},{"rootY":-0.4,"hips":[0,0],"chest":[6.7,-87.6],"neck":[6.7,-87.6],"head":[14.2,-152.6],"shR":[-50,-110.9],"elR":[-75.9,-0.3],"haR":[-115.5,45.9],"shL":[71.8,-108.7],"elL":[86.4,-5.6],"haL":[104,48.7],"hipR":[-29.1,35.2],"knR":[-51.7,182.7],"ftR":[-44.6,320.6],"hipL":[19,38.5],"knL":[11.7,179.6],"ftL":[42.8,326.8]},{"rootY":-0.7,"hips":[0,0],"chest":[6.9,-87.5],"neck":[6.9,-87.5],"head":[14.5,-152.5],"shR":[-51,-110.4],"elR":[-77.3,0.1],"haR":[-115.6,46.1],"shL":[72,-109],"elL":[87,-5.9],"haL":[106.6,47.7],"hipR":[-28.7,35.3],"knR":[-50.2,183],"ftR":[-44,320.7],"hipL":[19.8,38.6],"knL":[13.1,179.4],"ftL":[43.1,327.2]},{"rootY":-0.8,"hips":[0,0],"chest":[6.3,-87.6],"neck":[6.3,-87.6],"head":[14.7,-152.4],"shR":[-52.2,-111.3],"elR":[-78.6,-0.8],"haR":[-115.2,45.1],"shL":[71.5,-108.3],"elL":[87.3,-5.3],"haL":[108.5,48],"hipR":[-28.2,35.4],"knR":[-48.9,183.2],"ftR":[-43.6,320.8],"hipL":[20.9,38.6],"knL":[14.9,179.1],"ftL":[43.2,327.4]},{"rootY":-0.9,"hips":[0,0],"chest":[5.9,-87.6],"neck":[5.9,-87.6],"head":[14.6,-152.4],"shR":[-53.2,-111.7],"elR":[-79.8,-1.3],"haR":[-114.6,44.5],"shL":[70.9,-108.2],"elL":[87.2,-5.2],"haL":[110.1,48.4],"hipR":[-27.8,35.4],"knR":[-48.1,183.3],"ftR":[-43.3,320.8],"hipL":[21.5,38.6],"knL":[16,178.9],"ftL":[43,327.5]},{"rootY":-1,"hips":[0,0],"chest":[5.7,-87.6],"neck":[5.7,-87.6],"head":[14.7,-152.4],"shR":[-54,-111.5],"elR":[-80.7,-1.2],"haR":[-113.8,44.6],"shL":[70.3,-108.5],"elL":[86.7,-5.5],"haL":[111.1,47.8],"hipR":[-27.5,35.5],"knR":[-47.5,183.4],"ftR":[-43.3,320.8],"hipL":[22.1,38.6],"knL":[17.1,178.7],"ftL":[42.7,327.5]},{"rootY":-1.1,"hips":[0,0],"chest":[5.5,-87.6],"neck":[5.5,-87.6],"head":[14.3,-152.5],"shR":[-54.5,-111.7],"elR":[-80.9,-1.4],"haR":[-112.4,44.4],"shL":[69.8,-108.5],"elL":[86,-5.4],"haL":[111.6,47.5],"hipR":[-27.5,35.4],"knR":[-46.7,183.4],"ftR":[-42.9,320.8],"hipL":[22.2,38.8],"knL":[17.7,178.6],"ftL":[43,327.8]},{"rootY":-1.3,"hips":[0,0],"chest":[5.1,-87.6],"neck":[5.1,-87.6],"head":[14.1,-152.4],"shR":[-55.2,-111.7],"elR":[-81.1,-1.4],"haR":[-111,44.4],"shL":[69.1,-108.7],"elL":[85.2,-5.6],"haL":[111.4,47.6],"hipR":[-27.3,35.4],"knR":[-46.2,183.5],"ftR":[-42.9,321],"hipL":[22.5,38.8],"knL":[18.2,178.5],"ftL":[42.9,327.9]},{"rootY":-1.5,"hips":[0,0],"chest":[5.1,-87.6],"neck":[5.1,-87.6],"head":[13.8,-152.5],"shR":[-55.4,-111.6],"elR":[-80.2,-1.2],"haR":[-108.9,44.5],"shL":[68.7,-108.8],"elL":[84.4,-5.6],"haL":[110.9,47.8],"hipR":[-27.4,35.3],"knR":[-45.4,183.4],"ftR":[-42.6,321.1],"hipL":[22.4,39],"knL":[19,178.5],"ftL":[43.1,328]},{"rootY":-1.6,"hips":[0,0],"chest":[4.7,-87.6],"neck":[4.7,-87.6],"head":[13.5,-152.4],"shR":[-55.8,-111.3],"elR":[-79.6,-0.6],"haR":[-106.9,44.8],"shL":[68.2,-109.1],"elL":[83.1,-5.8],"haL":[109.8,48],"hipR":[-27.2,35.4],"knR":[-45.8,183.5],"ftR":[-43.1,321.3],"hipL":[22.6,39],"knL":[18.7,178.4],"ftL":[42.5,328.1]},{"rootY":-1.7,"hips":[0,0],"chest":[4.5,-87.6],"neck":[4.5,-87.6],"head":[13,-152.5],"shR":[-56.2,-111.1],"elR":[-78.3,-0.1],"haR":[-104.4,45.2],"shL":[67.8,-109.2],"elL":[82,-5.8],"haL":[108.3,48.6],"hipR":[-27.2,35.4],"knR":[-45.9,183.5],"ftR":[-43.4,321.4],"hipL":[22.6,39],"knL":[18.4,178.4],"ftL":[42.3,328.2]},{"rootY":-1.8,"hips":[0,0],"chest":[4.6,-87.6],"neck":[4.6,-87.6],"head":[12.6,-152.5],"shR":[-56.1,-111],"elR":[-76.6,0.4],"haR":[-101.5,45.8],"shL":[67.9,-109.5],"elL":[81.2,-6],"haL":[106.8,49.3],"hipR":[-27.5,35.3],"knR":[-45.9,183.4],"ftR":[-43.4,321.5],"hipL":[22.3,39.2],"knL":[18.1,178.5],"ftL":[42.4,328.3]},{"rootY":-1.8,"hips":[0,0],"chest":[4.3,-87.6],"neck":[4.3,-87.6],"head":[11.7,-152.6],"shR":[-56.3,-110.9],"elR":[-75.1,0.8],"haR":[-99.1,46.7],"shL":[67.8,-109.8],"elL":[80.2,-6.2],"haL":[105,50],"hipR":[-27.5,35.5],"knR":[-46.7,183.4],"ftR":[-44,321.6],"hipL":[22.2,39.1],"knL":[17.3,178.5],"ftL":[41.8,328.3]},{"rootY":-1.8,"hips":[0,0],"chest":[4.2,-87.6],"neck":[4.2,-87.6],"head":[11.1,-152.6],"shR":[-56.4,-110.8],"elR":[-73.3,1.3],"haR":[-96.6,47.7],"shL":[67.9,-109.8],"elL":[79.5,-6.2],"haL":[103.1,50.8],"hipR":[-27.6,35.6],"knR":[-47.3,183.3],"ftR":[-44.4,321.7],"hipL":[22.1,39.1],"knL":[16.6,178.5],"ftL":[41.4,328.3]},{"rootY":-1.7,"hips":[0,0],"chest":[3.8,-87.6],"neck":[3.8,-87.6],"head":[10.1,-152.6],"shR":[-56.6,-110.6],"elR":[-71.8,1.8],"haR":[-94.8,49.1],"shL":[67.7,-110.1],"elL":[78.5,-6.3],"haL":[100.5,51.7],"hipR":[-27.8,35.5],"knR":[-48.6,183.1],"ftR":[-45.3,321.6],"hipL":[21.6,39],"knL":[15.3,178.5],"ftL":[40.5,328.1]},{"rootY":-1.7,"hips":[0,0],"chest":[3.5,-87.5],"neck":[3.5,-87.5],"head":[9.7,-152.6],"shR":[-56.7,-110.3],"elR":[-70,2.4],"haR":[-93.2,50.8],"shL":[67.6,-110.4],"elL":[77.8,-6.6],"haL":[98.2,52.3],"hipR":[-28,35.6],"knR":[-49.8,182.9],"ftR":[-46.3,321.5],"hipL":[21.2,38.9],"knL":[13.8,178.5],"ftL":[39.6,328]},{"rootY":-1.7,"hips":[0,0],"chest":[3.1,-87.5],"neck":[3.1,-87.5],"head":[8.2,-152.6],"shR":[-56.8,-110.2],"elR":[-68.3,2.8],"haR":[-91.9,52.5],"shL":[67.4,-110.6],"elL":[76.9,-6.7],"haL":[95.5,52.7],"hipR":[-28,35.8],"knR":[-51.3,182.8],"ftR":[-47.7,321.5],"hipL":[20.9,38.8],"knL":[11.9,178.4],"ftL":[38.3,327.8]},{"rootY":-1.7,"hips":[0,0],"chest":[2.8,-87.5],"neck":[2.8,-87.5],"head":[7,-152.5],"shR":[-56.5,-109.9],"elR":[-66.6,3.2],"haR":[-90.8,54.2],"shL":[67.2,-111],"elL":[76.2,-7.1],"haL":[92.7,53],"hipR":[-28.3,35.8],"knR":[-52.8,182.5],"ftR":[-49.1,321.5],"hipL":[20.1,38.8],"knL":[10.2,178.4],"ftL":[37,327.8]},{"rootY":-1.8,"hips":[0,0],"chest":[2.5,-87.4],"neck":[2.5,-87.4],"head":[5.4,-152.5],"shR":[-56.2,-109.8],"elR":[-64.7,3.5],"haR":[-89.9,56],"shL":[66.7,-111.3],"elL":[75.2,-7.3],"haL":[89.7,53],"hipR":[-28.4,36],"knR":[-54.9,182.2],"ftR":[-51.1,321.7],"hipL":[19.7,38.6],"knL":[8.2,178.3],"ftL":[35.4,327.7]},{"rootY":-1.7,"hips":[0,0],"chest":[2.2,-87.4],"neck":[2.2,-87.4],"head":[4.1,-152.3],"shR":[-55.6,-109.6],"elR":[-62.6,3.7],"haR":[-88.9,57.6],"shL":[66.1,-111.5],"elL":[74.4,-7.5],"haL":[86.6,53],"hipR":[-28.6,36.1],"knR":[-57.2,181.8],"ftR":[-53.6,322],"hipL":[18.8,38.6],"knL":[5.8,178.3],"ftL":[33.8,327.8]},{"rootY":-1.5,"hips":[0,0],"chest":[1.7,-87.3],"neck":[1.7,-87.3],"head":[2.8,-152],"shR":[-54.8,-109.5],"elR":[-60.5,3.9],"haR":[-88.2,58.9],"shL":[65.1,-111.6],"elL":[73.4,-7.6],"haL":[83.5,52.9],"hipR":[-28.6,36.3],"knR":[-60.1,181.2],"ftR":[-56.3,322.1],"hipL":[18.1,38.5],"knL":[3.2,178.1],"ftL":[32,327.5]},{"rootY":-1,"hips":[0,0],"chest":[1.2,-87.2],"neck":[1.2,-87.2],"head":[1.1,-151.8],"shR":[-53.7,-109.5],"elR":[-58.2,3.9],"haR":[-87.2,59.6],"shL":[63.9,-111.6],"elL":[72.4,-7.7],"haL":[80.4,52.8],"hipR":[-28.6,36.5],"knR":[-62.9,180.6],"ftR":[-58.7,321.8],"hipL":[17.2,38.4],"knL":[0.5,178],"ftL":[30.5,327.2]},{"rootY":-0.5,"hips":[0,0],"chest":[0.9,-87.1],"neck":[0.9,-87.1],"head":[-0.1,-151.6],"shR":[-52.3,-109.4],"elR":[-55.4,3.8],"haR":[-85.7,60.3],"shL":[62.5,-111.7],"elL":[72,-7.8],"haL":[77.9,52.5],"hipR":[-28.4,36.7],"knR":[-65.6,179.9],"ftR":[-60.9,321.5],"hipL":[16.5,38.1],"knL":[-2.2,177.6],"ftL":[29,326.8]},{"rootY":-0.1,"hips":[0,0],"chest":[0.6,-87],"neck":[0.6,-87],"head":[-1.8,-151.1],"shR":[-50.8,-109.6],"elR":[-52.4,3.5],"haR":[-84,60.6],"shL":[61,-111.5],"elL":[71,-7.6],"haL":[75,52.6],"hipR":[-28.3,36.8],"knR":[-67.9,179.2],"ftR":[-62.8,321.1],"hipL":[15.7,38],"knL":[-4.1,177.5],"ftL":[27.5,326.5]},{"rootY":0.1,"hips":[0,0],"chest":[0.3,-86.9],"neck":[0.3,-86.9],"head":[-3.2,-150.8],"shR":[-48.9,-109.7],"elR":[-48.9,3.2],"haR":[-81.3,60.6],"shL":[59.2,-111.3],"elL":[69.5,-7.4],"haL":[72,52.8],"hipR":[-28.3,36.9],"knR":[-69.9,178.5],"ftR":[-64.7,320.8],"hipL":[14.6,37.8],"knL":[-6.3,177.3],"ftL":[25.8,326.3]},{"rootY":0.2,"hips":[0,0],"chest":[0,-86.8],"neck":[0,-86.8],"head":[-4.8,-150.4],"shR":[-47,-109.9],"elR":[-44.9,2.7],"haR":[-77.9,60.6],"shL":[57.3,-111],"elL":[68,-7.2],"haL":[69.1,52.9],"hipR":[-28.3,36.9],"knR":[-70.9,178.2],"ftR":[-65.7,320.7],"hipL":[13.8,37.7],"knL":[-8,177.2],"ftL":[24.5,326.2]},{"rootY":0.1,"hips":[0,0],"chest":[-0.4,-86.8],"neck":[-0.4,-86.8],"head":[-6.1,-150.2],"shR":[-45.6,-110],"elR":[-41.4,2.2],"haR":[-74.6,60.6],"shL":[55.5,-110.9],"elL":[66,-7.1],"haL":[66,52.7],"hipR":[-28.2,36.9],"knR":[-72,178],"ftR":[-67,320.9],"hipL":[12.9,37.7],"knL":[-10,177.3],"ftL":[23.3,326.1]},{"rootY":0.2,"hips":[0,0],"chest":[-0.6,-86.7],"neck":[-0.6,-86.7],"head":[-6.8,-149.9],"shR":[-43.8,-110.4],"elR":[-37.7,1.4],"haR":[-70.6,60.3],"shL":[53.5,-110.6],"elL":[63.5,-6.8],"haL":[62.3,52.7],"hipR":[-28.1,37],"knR":[-72.9,177.7],"ftR":[-68.4,320.9],"hipL":[12.1,37.7],"knL":[-11.6,177.3],"ftL":[22,326.1]},{"rootY":0.2,"hips":[0,0],"chest":[-1.3,-86.6],"neck":[-1.3,-86.6],"head":[-8.5,-149.7],"shR":[-42.4,-110.1],"elR":[-34.1,1],"haR":[-66.3,60.6],"shL":[51.1,-110.6],"elL":[60.9,-6.8],"haL":[58.3,52.5],"hipR":[-27.9,37.1],"knR":[-74,177.5],"ftR":[-69.8,321.1],"hipL":[11.5,37.6],"knL":[-13.2,177.3],"ftL":[20.9,325.9]},{"rootY":0.1,"hips":[0,0],"chest":[-1.8,-86.5],"neck":[-1.8,-86.5],"head":[-9.7,-149.6],"shR":[-41.3,-110.4],"elR":[-30.8,0.1],"haR":[-62.1,60.2],"shL":[49,-110.1],"elL":[57.7,-6.4],"haL":[53.8,52.5],"hipR":[-27.8,37.1],"knR":[-74.8,177.3],"ftR":[-70.8,321.2],"hipL":[10.7,37.8],"knL":[-14.7,177.4],"ftL":[19.9,325.9]},{"rootY":0.1,"hips":[0,0],"chest":[-2.3,-86.4],"neck":[-2.3,-86.4],"head":[-10.9,-149.4],"shR":[-39.6,-110.7],"elR":[-27,-0.8],"haR":[-56.9,59.9],"shL":[46.7,-109.7],"elL":[54.2,-6],"haL":[48.7,52.6],"hipR":[-27.6,37.2],"knR":[-75.7,177],"ftR":[-71.8,321.3],"hipL":[10,37.8],"knL":[-16.2,177.5],"ftL":[19.1,326]},{"rootY":0,"hips":[0,0],"chest":[-3.2,-86.2],"neck":[-3.2,-86.2],"head":[-12.1,-149.1],"shR":[-39.1,-111.4],"elR":[-24.2,-2.2],"haR":[-52.5,59.1],"shL":[44.8,-108.8],"elL":[51.3,-5.2],"haL":[44.9,53.9],"hipR":[-27.6,37],"knR":[-76.2,176.7],"ftR":[-72.3,321.4],"hipL":[9.3,38.2],"knL":[-17.3,177.8],"ftL":[18.6,326.2]},{"rootY":0,"hips":[0,0],"chest":[-3.4,-86.2],"neck":[-3.4,-86.2],"head":[-12.9,-149.1],"shR":[-37.4,-110.8],"elR":[-20.8,-2],"haR":[-47.4,59.6],"shL":[42.5,-109.3],"elL":[47.8,-5.6],"haL":[38.9,52.1],"hipR":[-27.5,37],"knR":[-77.5,176.4],"ftR":[-73.4,321.3],"hipL":[8.3,38.2],"knL":[-19.1,178],"ftL":[17.9,325.9]},{"rootY":-0.1,"hips":[0,0],"chest":[-3.8,-86],"neck":[-3.8,-86],"head":[-14.2,-148.7],"shR":[-36.4,-110.9],"elR":[-18.1,-2.5],"haR":[-42.8,59.6],"shL":[40.6,-109],"elL":[44.5,-5.4],"haL":[33.9,51.9],"hipR":[-27.2,37],"knR":[-78.3,176.1],"ftR":[-73.9,321.1],"hipL":[7.8,38.3],"knL":[-20.2,178.1],"ftL":[17.6,325.9]},{"rootY":-0.3,"hips":[0,0],"chest":[-4.6,-85.9],"neck":[-4.6,-85.9],"head":[-15.4,-148.4],"shR":[-37.2,-111.5],"elR":[-17,-3.7],"haR":[-40.1,58.5],"shL":[39.6,-108.2],"elL":[42.1,-4.6],"haL":[29.6,52.4],"hipR":[-27.2,36.9],"knR":[-79.2,175.7],"ftR":[-74.2,320.8],"hipL":[7.4,38.6],"knL":[-20.5,178.5],"ftL":[17.2,326.2]},{"rootY":-0.3,"hips":[0,0],"chest":[-5,-85.7],"neck":[-5,-85.7],"head":[-16,-148.3],"shR":[-36.7,-111.9],"elR":[-14.6,-4.4],"haR":[-36.3,58],"shL":[38.2,-107.5],"elL":[39.6,-4.1],"haL":[25.2,52.9],"hipR":[-26.7,37.2],"knR":[-80,175.5],"ftR":[-74.7,320.6],"hipL":[7.5,38.5],"knL":[-20.7,178.5],"ftL":[17.2,326.1]},{"rootY":-0.4,"hips":[0,0],"chest":[-5.5,-85.5],"neck":[-5.5,-85.5],"head":[-17.2,-147.9],"shR":[-36.8,-111.8],"elR":[-13.1,-4.7],"haR":[-33.7,57.9],"shL":[37,-107.3],"elL":[37.2,-3.8],"haL":[20.9,52.7],"hipR":[-26.6,37.2],"knR":[-80.6,175.3],"ftR":[-75,320.2],"hipL":[7.2,38.8],"knL":[-21.2,178.7],"ftL":[17.1,326.1]},{"rootY":-0.4,"hips":[0,0],"chest":[-5.8,-85.3],"neck":[-5.8,-85.3],"head":[-18.2,-147.4],"shR":[-36.1,-111.9],"elR":[-10.6,-5.1],"haR":[-30.9,57.7],"shL":[35.5,-106.9],"elL":[34.2,-3.3],"haL":[16.3,53],"hipR":[-26.4,37.2],"knR":[-81,175],"ftR":[-74.8,319.8],"hipL":[7.2,38.9],"knL":[-20.8,179],"ftL":[17.2,326.1]},{"rootY":-0.4,"hips":[0,0],"chest":[-6.4,-85.1],"neck":[-6.4,-85.1],"head":[-19.1,-147.1],"shR":[-36.3,-112.3],"elR":[-9.5,-5.8],"haR":[-29.2,57.1],"shL":[34.4,-106.2],"elL":[31.6,-2.7],"haL":[12.3,53.2],"hipR":[-26.5,37],"knR":[-81.4,174.6],"ftR":[-73.6,319.5],"hipL":[6.7,39.2],"knL":[-21.2,179.3],"ftL":[17.6,326]},{"rootY":-0.5,"hips":[0,0],"chest":[-7,-84.9],"neck":[-7,-84.9],"head":[-20,-146.8],"shR":[-36.3,-112.3],"elR":[-8.8,-5.7],"haR":[-28,57.1],"shL":[33,-105.8],"elL":[28.5,-2.3],"haL":[8.3,53.4],"hipR":[-26.4,36.9],"knR":[-81.9,174.2],"ftR":[-72.4,318.9],"hipL":[6.7,39.5],"knL":[-21.3,179.7],"ftL":[18,326.2]},{"rootY":-0.5,"hips":[0,0],"chest":[-7,-84.6],"neck":[-7,-84.6],"head":[-20.6,-146.3],"shR":[-36.4,-112.4],"elR":[-7.7,-6.4],"haR":[-27.2,56.4],"shL":[32.8,-105.2],"elL":[27.1,-1.7],"haL":[5.7,53.7],"hipR":[-26,37.2],"knR":[-82.4,174.1],"ftR":[-70.6,318.3],"hipL":[7.2,39.5],"knL":[-20.2,179.8],"ftL":[19.1,326.1]},{"rootY":-0.3,"hips":[0,0],"chest":[-7.2,-84.7],"neck":[-7.2,-84.7],"head":[-21,-146.3],"shR":[-36.4,-112.8],"elR":[-7.3,-7],"haR":[-27,55.9],"shL":[32.5,-104.9],"elL":[25.8,-1.4],"haL":[3.4,53.6],"hipR":[-25.8,37.2],"knR":[-83.5,173.6],"ftR":[-69,317.1],"hipL":[6.6,39.4],"knL":[-20.5,180],"ftL":[20.5,325.6]},{"rootY":-0.5,"hips":[0,0],"chest":[-7.8,-84],"neck":[-7.8,-84],"head":[-22.1,-145.4],"shR":[-36.8,-112.2],"elR":[-7.6,-6.3],"haR":[-27.5,56.5],"shL":[31.2,-104.2],"elL":[23.4,-0.8],"haL":[0.3,54],"hipR":[-25.7,37.3],"knR":[-83.2,173.4],"ftR":[-67.1,316.5],"hipL":[8.1,39.9],"knL":[-18.1,180.5],"ftL":[21.6,326.1]},{"rootY":-0.2,"hips":[0,0],"chest":[-8.1,-83.8],"neck":[-8.1,-83.8],"head":[-22.7,-145.1],"shR":[-36.9,-112.4],"elR":[-7.8,-6.7],"haR":[-28.4,56],"shL":[30.8,-103.6],"elL":[22.1,-0.2],"haL":[-1.6,54.4],"hipR":[-25.5,37.4],"knR":[-83.8,173.1],"ftR":[-65.4,315.3],"hipL":[8.4,39.9],"knL":[-17.1,180.7],"ftL":[23.1,325.7]},{"rootY":0.2,"hips":[0,0],"chest":[-8.3,-83.6],"neck":[-8.3,-83.6],"head":[-23.2,-144.7],"shR":[-37.5,-112.4],"elR":[-8.2,-6.9],"haR":[-30,55.6],"shL":[30.6,-103.3],"elL":[21.1,0],"haL":[-2.7,54.6],"hipR":[-25.2,37.6],"knR":[-84.6,172.9],"ftR":[-63.5,313.9],"hipL":[8.9,39.9],"knL":[-15.3,181],"ftL":[24.9,325.2]},{"rootY":0.4,"hips":[0,0],"chest":[-8.8,-83.3],"neck":[-8.8,-83.3],"head":[-24,-144.3],"shR":[-38.5,-112.2],"elR":[-9.2,-6.8],"haR":[-32,55.5],"shL":[30.6,-102.7],"elL":[20.5,0.6],"haL":[-3.2,54.9],"hipR":[-25.4,37.5],"knR":[-84.5,172.7],"ftR":[-61.4,312.5],"hipL":[9.1,40.2],"knL":[-14.4,181.5],"ftL":[27,325.2]},{"rootY":0.6,"hips":[0,0],"chest":[-8.8,-83.2],"neck":[-8.8,-83.2],"head":[-24.1,-144.1],"shR":[-39.2,-112.5],"elR":[-10.6,-7.2],"haR":[-34.1,54.7],"shL":[31,-102.4],"elL":[20.7,0.9],"haL":[-2.7,55.4],"hipR":[-25.2,37.5],"knR":[-84.8,172.6],"ftR":[-58.8,311],"hipL":[9.3,40.3],"knL":[-12.9,181.9],"ftL":[29.9,324.6]},{"rootY":1.3,"hips":[0,0],"chest":[-8.9,-82.9],"neck":[-8.9,-82.9],"head":[-24.6,-143.7],"shR":[-39.3,-112.2],"elR":[-11.5,-7.2],"haR":[-36.1,54.2],"shL":[30.9,-102.1],"elL":[20.8,1.1],"haL":[-2.2,55.6],"hipR":[-25.1,37.6],"knR":[-84.4,172.9],"ftR":[-55.6,309.5],"hipL":[10,40.4],"knL":[-10.6,182.3],"ftL":[32.8,324]},{"rootY":2.2,"hips":[0,0],"chest":[-8.9,-83.1],"neck":[-8.9,-83.1],"head":[-24.6,-143.7],"shR":[-40.3,-112.6],"elR":[-12.7,-8],"haR":[-38.6,53],"shL":[31.8,-102],"elL":[21.6,1.2],"haL":[-0.2,55.6],"hipR":[-25.1,37.5],"knR":[-84.3,173],"ftR":[-51.8,307.6],"hipL":[9.6,40.5],"knL":[-9.4,182.7],"ftL":[36.3,322.8]},{"rootY":3,"hips":[0,0],"chest":[-9.1,-82.5],"neck":[-9.1,-82.5],"head":[-24.9,-143.1],"shR":[-42.7,-112.6],"elR":[-15,-8.4],"haR":[-42.1,52.1],"shL":[33.8,-100.9],"elL":[24,2],"haL":[3.6,56.4],"hipR":[-24.9,37.8],"knR":[-82.9,173.6],"ftR":[-46.7,305.9],"hipL":[10.9,40.6],"knL":[-6,183],"ftL":[40.3,322.1]},{"rootY":4,"hips":[0,0],"chest":[-8.9,-82.3],"neck":[-8.9,-82.3],"head":[-24.8,-142.9],"shR":[-43,-112.6],"elR":[-16,-8.8],"haR":[-44.6,51.2],"shL":[34.5,-100.5],"elL":[25.9,2.3],"haL":[7.2,56.5],"hipR":[-24.9,37.7],"knR":[-81.6,174.3],"ftR":[-41.7,304],"hipL":[11.4,40.8],"knL":[-3.2,183.5],"ftL":[44.8,321]},{"rootY":5.2,"hips":[0,0],"chest":[-8.9,-82],"neck":[-8.9,-82],"head":[-24.7,-142.5],"shR":[-43.2,-112.4],"elR":[-16.5,-9.4],"haR":[-46.8,50],"shL":[34.7,-100.2],"elL":[28.2,2.4],"haL":[11.2,56.3],"hipR":[-24.9,37.7],"knR":[-79.8,175],"ftR":[-37,302.1],"hipL":[11.8,41.1],"knL":[-0.7,183.9],"ftL":[49.5,319.6]},{"rootY":6.8,"hips":[0,0],"chest":[-8.5,-81.8],"neck":[-8.5,-81.8],"head":[-24.2,-142.1],"shR":[-43.1,-112.2],"elR":[-17.3,-9.4],"haR":[-49.5,49.3],"shL":[35.3,-99.8],"elL":[31.9,2.3],"haL":[17.2,55.7],"hipR":[-25.4,37.4],"knR":[-77.4,175.8],"ftR":[-31.2,299.7],"hipL":[11.8,41.4],"knL":[2.5,184.5],"ftL":[55,317.6]},{"rootY":8.6,"hips":[0,0],"chest":[-7.7,-81.3],"neck":[-7.7,-81.3],"head":[-23.2,-141.6],"shR":[-42.1,-111.6],"elR":[-18.2,-8.9],"haR":[-52.2,48.9],"shL":[36,-99.6],"elL":[37,2.2],"haL":[25.1,54.5],"hipR":[-25.7,37],"knR":[-73.9,176.7],"ftR":[-24.7,297.3],"hipL":[11.8,42],"knL":[4.9,185.2],"ftL":[60.8,315.1]},{"rootY":10.9,"hips":[0,0],"chest":[-8,-81.5],"neck":[-8,-81.5],"head":[-23.2,-141.7],"shR":[-43.3,-111.9],"elR":[-22.1,-9],"haR":[-58.3,47.8],"shL":[36.5,-99.5],"elL":[42.3,1.4],"haL":[34.2,52.3],"hipR":[-26.5,36.5],"knR":[-71.6,177.5],"ftR":[-19.2,293.9],"hipL":[11.2,42.2],"knL":[4.8,185.4],"ftL":[65.9,309.7]},{"rootY":12.9,"hips":[0,0],"chest":[-8.2,-81.1],"neck":[-8.2,-81.1],"head":[-23,-141.2],"shR":[-44.1,-111.8],"elR":[-27.4,-8.1],"haR":[-65.9,47.4],"shL":[37.1,-98.9],"elL":[48.6,0.4],"haL":[45,49.7],"hipR":[-27.2,36.1],"knR":[-68.7,178.2],"ftR":[-14.2,289.9],"hipL":[11.2,42.6],"knL":[4.5,185.7],"ftL":[71.1,300.8]},{"rootY":15,"hips":[0,0],"chest":[-8.9,-80.7],"neck":[-8.9,-80.7],"head":[-23.3,-140.6],"shR":[-45.6,-111.3],"elR":[-34.2,-7.3],"haR":[-75.5,46.4],"shL":[36.7,-98.7],"elL":[55.5,-1.9],"haL":[57.2,45.1],"hipR":[-28,35.7],"knR":[-66.6,178.8],"ftR":[-10.4,285.5],"hipL":[12,42.9],"knL":[1.9,184.4],"ftL":[72,287.3]},{"rootY":17.9,"hips":[0,0],"chest":[-9.4,-80.4],"neck":[-9.4,-80.4],"head":[-23.3,-140.3],"shR":[-48.6,-110.5],"elR":[-44.6,-6],"haR":[-89.2,44.9],"shL":[38.1,-99],"elL":[64.9,-6.3],"haL":[73.1,37.7],"hipR":[-28.6,35.4],"knR":[-65.3,179.2],"ftR":[-6.8,280.9],"hipL":[12.2,43.2],"knL":[-1.8,180.2],"ftL":[66.7,272.3]},{"rootY":20.8,"hips":[0,0],"chest":[-10.2,-80.2],"neck":[-10.2,-80.2],"head":[-23,-140.2],"shR":[-52.3,-109.6],"elR":[-58.9,-5.2],"haR":[-107.6,41],"shL":[39.5,-99.7],"elL":[74.5,-12.2],"haL":[90,27.9],"hipR":[-29.7,34.5],"knR":[-63.4,179.6],"ftR":[-2.5,277.3],"hipL":[11.3,43.7],"knL":[-5,172.7],"ftL":[56,260.3]},{"rootY":22.6,"hips":[0,0],"chest":[-10.7,-79.8],"neck":[-10.7,-79.8],"head":[-22.5,-140.1],"shR":[-54.6,-108.8],"elR":[-74,-4.9],"haR":[-126.6,33.7],"shL":[40.7,-99.6],"elL":[86.9,-18.9],"haL":[109,14.6],"hipR":[-29.8,34.4],"knR":[-58.7,181.1],"ftR":[2.9,275.6],"hipL":[11.5,43.9],"knL":[-6.9,161.3],"ftL":[41.4,256]},{"rootY":20.9,"hips":[0,0],"chest":[-10.4,-79.9],"neck":[-10.4,-79.9],"head":[-21.4,-140.4],"shR":[-56.4,-108.8],"elR":[-88.5,-6.2],"haR":[-143.2,21.3],"shL":[43.1,-99.9],"elL":[100.3,-28.3],"haL":[129.8,-1.4],"hipR":[-30.1,34],"knR":[-50.7,182.6],"ftR":[9.6,277.2],"hipL":[11.2,44.2],"knL":[-10.2,149.4],"ftL":[26.5,260.6]},{"rootY":16.3,"hips":[0,0],"chest":[-9.3,-80.5],"neck":[-9.3,-80.5],"head":[-20.1,-141],"shR":[-56.8,-108.7],"elR":[-100.1,-8],"haR":[-153.8,6.5],"shL":[45.8,-101.1],"elL":[113.6,-37.6],"haL":[149.5,-18.3],"hipR":[-30.8,33.4],"knR":[-40.7,182.2],"ftR":[15.3,280],"hipL":[10.6,44.6],"knL":[-15.2,141.4],"ftL":[12.1,272.7]},{"rootY":9.6,"hips":[0,0],"chest":[-7.7,-80.9],"neck":[-7.7,-80.9],"head":[-18.4,-141.7],"shR":[-56,-107.7],"elR":[-108.5,-9.8],"haR":[-158.1,-6.9],"shL":[48,-103],"elL":[123.3,-46.5],"haL":[166.5,-34.1],"hipR":[-31.9,32.2],"knR":[-33.9,178.4],"ftR":[16.7,281.5],"hipL":[9.3,45.3],"knL":[-20.9,139.2],"ftL":[-1.5,287.7]},{"rootY":1.2,"hips":[0,0],"chest":[-5.7,-82],"neck":[-5.7,-82],"head":[-17,-143],"shR":[-54.4,-106.5],"elR":[-115.1,-11.8],"haR":[-159.8,-17.8],"shL":[50.4,-106.1],"elL":[133.3,-54.9],"haL":[181.6,-48.7],"hipR":[-32.9,31.2],"knR":[-30.8,172.2],"ftR":[9.3,283.3],"hipL":[8,45.6],"knL":[-25.4,143.1],"ftL":[-14.3,302.7]},{"rootY":-5.2,"hips":[0,0],"chest":[-2.8,-83.3],"neck":[-2.8,-83.3],"head":[-14.3,-144.8],"shR":[-51.7,-105.4],"elR":[-118.9,-14.1],"haR":[-159.5,-26.7],"shL":[53.2,-109.6],"elL":[142.1,-64.3],"haL":[194.7,-63.6],"hipR":[-33.6,30.6],"knR":[-29.7,164.2],"ftR":[2.6,276.6],"hipL":[7.2,45.5],"knL":[-27.4,149.3],"ftL":[-25.3,312.7]},{"rootY":-6.7,"hips":[0,0],"chest":[0,-84.7],"neck":[0,-84.7],"head":[-11.6,-146.7],"shR":[-50.4,-105.6],"elR":[-120.6,-16.4],"haR":[-159.8,-33.6],"shL":[57.5,-111.7],"elL":[151.2,-73.2],"haL":[206.4,-77.3],"hipR":[-35.2,29.2],"knR":[-33.6,157.1],"ftR":[0.8,255.8],"hipL":[5.2,45.4],"knL":[-30.3,153.3],"ftL":[-34.1,315.6]},{"rootY":-2.9,"hips":[0,0],"chest":[2.6,-86],"neck":[2.6,-86],"head":[-8.6,-148.5],"shR":[-48.3,-105.3],"elR":[-119.4,-16.7],"haR":[-159.3,-36],"shL":[60.8,-113.9],"elL":[158.2,-82.6],"haL":[214.5,-90.8],"hipR":[-36.8,27.7],"knR":[-43.1,151.2],"ftR":[-2.8,226.7],"hipL":[3.5,44.9],"knL":[-32.4,153.5],"ftL":[-41.2,315.2]},{"rootY":5.7,"hips":[0,0],"chest":[5.5,-86.6],"neck":[5.5,-86.6],"head":[-5,-149.5],"shR":[-46.1,-104.3],"elR":[-116.1,-14.9],"haR":[-158.4,-33.9],"shL":[64.8,-115],"elL":[164.6,-89.2],"haL":[221.1,-101.6],"hipR":[-37.8,26.9],"knR":[-54.8,147.1],"ftR":[-9.9,194.8],"hipL":[3.6,44.1],"knL":[-29.1,151],"ftL":[-46.4,313.1]},{"rootY":18.4,"hips":[0,0],"chest":[8,-86.9],"neck":[8,-86.9],"head":[-1.5,-150.3],"shR":[-44.2,-103.4],"elR":[-110.7,-11.3],"haR":[-156.9,-28.3],"shL":[68.1,-115.4],"elL":[168.7,-91.8],"haL":[224.3,-108.4],"hipR":[-38.6,25.8],"knR":[-69.4,144.1],"ftR":[-21.8,164.3],"hipL":[3.4,43.3],"knL":[-23.8,148.1],"ftL":[-52.5,308]},{"rootY":29,"hips":[0,0],"chest":[9.4,-87],"neck":[9.4,-87],"head":[-0.1,-150.4],"shR":[-43.5,-103],"elR":[-101,-5],"haR":[-153.2,-17.3],"shL":[70.4,-115],"elL":[169.5,-87.8],"haL":[223.8,-107.4],"hipR":[-38.6,25.6],"knR":[-86,145.3],"ftR":[-39.7,146.2],"hipL":[4.3,41.7],"knL":[-21,142.8],"ftL":[-50.4,298.1]},{"rootY":37.7,"hips":[0,0],"chest":[9.3,-87.1],"neck":[9.3,-87.1],"head":[-1.5,-150.3],"shR":[-43.5,-102.9],"elR":[-87.7,1.7],"haR":[-145.4,0.3],"shL":[70.4,-115.1],"elL":[164.9,-77],"haL":[217.4,-97],"hipR":[-37.5,26.6],"knR":[-104.4,149.1],"ftR":[-63.3,145.1],"hipL":[6.3,39.4],"knL":[-19.2,139.5],"ftL":[-46.1,289]},{"rootY":42.8,"hips":[0,0],"chest":[7.3,-87.3],"neck":[7.3,-87.3],"head":[-4.7,-150],"shR":[-45.1,-102.5],"elR":[-74.4,7],"haR":[-133.7,20.7],"shL":[67.9,-115.9],"elL":[154.3,-63.5],"haL":[205.1,-80],"hipR":[-36.1,28],"knR":[-122.2,148.8],"ftR":[-90.5,165.4],"hipL":[8.1,36.8],"knL":[-19.8,140.2],"ftL":[-46.3,284]},{"rootY":46,"hips":[0,0],"chest":[3.8,-87.4],"neck":[3.8,-87.4],"head":[-9.2,-149.8],"shR":[-47.5,-101.4],"elR":[-60.9,10.8],"haR":[-118.2,38.5],"shL":[63.3,-117.3],"elL":[139.6,-52.7],"haL":[187.5,-61.3],"hipR":[-35,28.7],"knR":[-134.1,140.4],"ftR":[-119.6,204],"hipL":[9.6,34.7],"knL":[-22.1,141.3],"ftL":[-47.1,280.7]},{"rootY":48.2,"hips":[0,0],"chest":[1.2,-87.4],"neck":[1.2,-87.4],"head":[-12.8,-149.5],"shR":[-49,-100.7],"elR":[-46.7,11.4],"haR":[-98.4,51.6],"shL":[59.1,-118.6],"elL":[123.8,-43.8],"haL":[166.6,-41.7],"hipR":[-33.2,29.6],"knR":[-133.3,130.9],"ftR":[-148.3,248.9],"hipL":[12.2,31.7],"knL":[-22.5,142.1],"ftL":[-46.1,277.7]},{"rootY":47.4,"hips":[0,0],"chest":[-0.6,-87.3],"neck":[-0.6,-87.3],"head":[-15.8,-149.2],"shR":[-49,-99.3],"elR":[-33,10.8],"haR":[-76.6,61.6],"shL":[55,-120.3],"elL":[106.6,-36],"haL":[139.6,-22.9],"hipR":[-31.7,30.7],"knR":[-123.4,124.8],"ftR":[-169.4,270.8],"hipL":[13.6,29.6],"knL":[-22.6,144.9],"ftL":[-44.9,278.5]},{"rootY":41.8,"hips":[0,0],"chest":[-1.3,-87.2],"neck":[-1.3,-87.2],"head":[-17,-149],"shR":[-47.4,-98.7],"elR":[-18.7,8.2],"haR":[-53.6,66.1],"shL":[52.1,-121],"elL":[89.2,-29.4],"haL":[110.3,-6.1],"hipR":[-31,31.5],"knR":[-114.7,117.7],"ftR":[-158.6,259],"hipL":[14,28.9],"knL":[-21.9,149.8],"ftL":[-43.7,283.7]},{"rootY":39.1,"hips":[0,0],"chest":[-2.6,-87.2],"neck":[-2.6,-87.2],"head":[-18.5,-149.1],"shR":[-45.9,-98],"elR":[-7.3,5.6],"haR":[-33,68.3],"shL":[48.3,-122.1],"elL":[69,-25.2],"haL":[77.3,5.9],"hipR":[-30.7,32.1],"knR":[-105,107.4],"ftR":[-142,233.5],"hipL":[14.3,29.6],"knL":[-22.3,152.6],"ftL":[-42.6,287.3]},{"rootY":36.8,"hips":[0,0],"chest":[-2.6,-87.3],"neck":[-2.6,-87.3],"head":[-18.2,-149.5],"shR":[-42.7,-97.5],"elR":[3.9,2.8],"haR":[-13.4,67.7],"shL":[45.3,-122.9],"elL":[50.7,-23.2],"haL":[44.3,13.2],"hipR":[-28.2,33.2],"knR":[-90,97.1],"ftR":[-111.8,216.9],"hipL":[16.9,26.2],"knL":[-23,152.2],"ftL":[-39.4,287.1]},{"rootY":36.7,"hips":[0,0],"chest":[-3.8,-87.3],"neck":[-3.8,-87.3],"head":[-19.1,-149.9],"shR":[-40.6,-97.8],"elR":[12.1,-0.6],"haR":[1.5,64.9],"shL":[41.7,-122.8],"elL":[35.5,-22.1],"haL":[12.5,16.8],"hipR":[-27.5,33],"knR":[-72.9,83.9],"ftR":[-70.2,203],"hipL":[18.5,25.8],"knL":[-21.6,153.8],"ftL":[-38.6,287.3]},{"rootY":34.5,"hips":[0,0],"chest":[-2.2,-87.4],"neck":[-2.2,-87.4],"head":[-17.6,-150.2],"shR":[-35.9,-98.2],"elR":[19.8,-2.5],"haR":[15.1,62.6],"shL":[40.7,-122.8],"elL":[25.3,-22.3],"haL":[-13.1,16.2],"hipR":[-27,32.6],"knR":[-53.1,72.2],"ftR":[-30.6,193.9],"hipL":[20,26],"knL":[-17.1,156.3],"ftL":[-35.5,289.6]},{"rootY":31.3,"hips":[0,0],"chest":[-0.8,-87.4],"neck":[-0.8,-87.4],"head":[-16,-150.3],"shR":[-31.4,-98.1],"elR":[24.6,-2.3],"haR":[24.8,61.9],"shL":[39.8,-122.8],"elL":[17,-23.6],"haL":[-33.5,12.1],"hipR":[-27.4,32.2],"knR":[-33.2,66.2],"ftR":[3.4,188.9],"hipL":[20.3,27.8],"knL":[-14.4,159.7],"ftL":[-32.4,292]},{"rootY":29.3,"hips":[0,0],"chest":[0.2,-87.5],"neck":[0.2,-87.5],"head":[-14.3,-150.7],"shR":[-28.8,-98.3],"elR":[27,-2.3],"haR":[30.3,60.9],"shL":[39.8,-122.8],"elL":[8.9,-25.7],"haL":[-48.9,5.8],"hipR":[-25.6,33],"knR":[-15.9,63.5],"ftR":[31.6,187.2],"hipL":[22.5,27.1],"knL":[-10.2,161],"ftL":[-32,293.5]},{"rootY":25.9,"hips":[0,0],"chest":[0.3,-87.5],"neck":[0.3,-87.5],"head":[-13.2,-151],"shR":[-29.2,-98.8],"elR":[27.4,-3.3],"haR":[31.5,59.2],"shL":[40.7,-122.2],"elL":[0.7,-28.2],"haL":[-60.5,-1.7],"hipR":[-24.6,33],"knR":[-1.6,66.3],"ftR":[56.2,191.8],"hipL":[24.2,27.7],"knL":[-4.8,164],"ftL":[-31.9,297.3]},{"rootY":23.7,"hips":[0,0],"chest":[0.8,-87.6],"neck":[0.8,-87.6],"head":[-11.8,-151.4],"shR":[-30.5,-97.6],"elR":[26.7,-2.7],"haR":[30.9,59.5],"shL":[42.6,-123.4],"elL":[-7.2,-33.4],"haL":[-69.4,-11.2],"hipR":[-22.3,34],"knR":[11.5,74.6],"ftR":[75.8,201.6],"hipL":[27.3,28.4],"knL":[1.5,165.8],"ftL":[-31.2,298.4]},{"rootY":20.5,"hips":[0,0],"chest":[1.4,-87.6],"neck":[1.4,-87.6],"head":[-10.8,-151.7],"shR":[-33.8,-97.5],"elR":[23.1,-3],"haR":[26.5,59.5],"shL":[45.7,-123.6],"elL":[-12.2,-37.9],"haL":[-74.6,-19.8],"hipR":[-20.8,34.5],"knR":[23.3,85.9],"ftR":[88.9,216.7],"hipL":[29.2,29.7],"knL":[7.3,168.2],"ftL":[-30.3,300.9]},{"rootY":18.4,"hips":[0,0],"chest":[1.6,-87.6],"neck":[1.6,-87.6],"head":[-10.1,-151.9],"shR":[-36.3,-96.5],"elR":[18.3,-1.5],"haR":[20.8,61.3],"shL":[47.3,-124.5],"elL":[-15.9,-41.9],"haL":[-78.9,-27.9],"hipR":[-18.8,35.4],"knR":[32.5,97.3],"ftR":[93.3,234.3],"hipL":[31.2,30.4],"knL":[11.3,169.9],"ftL":[-31,302.9]},{"rootY":17,"hips":[0,0],"chest":[1.7,-87.5],"neck":[1.7,-87.5],"head":[-9.5,-151.9],"shR":[-41.8,-97.1],"elR":[8.7,-1.1],"haR":[9.7,62.4],"shL":[51.6,-123.7],"elL":[-14.2,-43.3],"haL":[-77.2,-32.8],"hipR":[-14.9,36.3],"knR":[41,108.6],"ftR":[90.9,253],"hipL":[34.4,28.9],"knL":[13.7,169.4],"ftL":[-33.5,303.2]},{"rootY":15.9,"hips":[0,0],"chest":[2.2,-87.3],"neck":[2.2,-87.3],"head":[-8.7,-151.8],"shR":[-45.8,-97.8],"elR":[-3.2,1.1],"haR":[-4.5,65],"shL":[55.3,-122.5],"elL":[-11.4,-43.3],"haL":[-74.7,-35.4],"hipR":[-16.5,35.6],"knR":[47.8,120.2],"ftR":[85.2,269.7],"hipL":[32.9,31.7],"knL":[15.2,172.9],"ftL":[-33.4,305.7]},{"rootY":16.5,"hips":[0,0],"chest":[0,-87.4],"neck":[0,-87.4],"head":[-10.6,-152],"shR":[-51.7,-97.5],"elR":[-18.3,3.9],"haR":[-24.2,68.4],"shL":[55.7,-122.5],"elL":[-9.1,-43.6],"haL":[-72.3,-36.5],"hipR":[-13,36.5],"knR":[49.6,133.7],"ftR":[72.5,286.3],"hipL":[35.2,31.1],"knL":[16.4,172.2],"ftL":[-37.7,302.4]},{"rootY":17.9,"hips":[0,0],"chest":[-1.4,-87.3],"neck":[-1.4,-87.3],"head":[-11.2,-152.1],"shR":[-56,-98.1],"elR":[-32.9,5.8],"haR":[-45.3,70.4],"shL":[56.4,-121.5],"elL":[-3.6,-42.8],"haL":[-67.7,-35.3],"hipR":[-12.3,36.6],"knR":[48.5,145.7],"ftR":[59.8,299],"hipL":[35.2,32],"knL":[17.2,173.2],"ftL":[-41.4,300.6]},{"rootY":17.9,"hips":[0,0],"chest":[-1.8,-87.2],"neck":[-1.8,-87.2],"head":[-11.3,-152],"shR":[-59.5,-98.8],"elR":[-48,7.4],"haR":[-67.5,71.2],"shL":[57.6,-120.4],"elL":[4.9,-41.5],"haL":[-60.3,-31.4],"hipR":[-11.6,35.9],"knR":[50.5,151.2],"ftR":[61.4,304.6],"hipL":[34.7,33.1],"knL":[19,174.6],"ftL":[-43.3,299.4]},{"rootY":19.3,"hips":[0,0],"chest":[-1.3,-87.6],"neck":[-1.3,-87.6],"head":[-10.4,-152.4],"shR":[-60.8,-98],"elR":[-60.7,10.4],"haR":[-88,71.9],"shL":[58.7,-120.7],"elL":[15.7,-41.7],"haL":[-49.2,-26.7],"hipR":[-13,35.4],"knR":[48.1,152.6],"ftR":[64.4,305.2],"hipL":[33.7,34],"knL":[18.2,175.3],"ftL":[-44.9,297.5]},{"rootY":21.4,"hips":[0,0],"chest":[0.5,-87.7],"neck":[0.5,-87.7],"head":[-8.4,-152.5],"shR":[-60.8,-97.4],"elR":[-70.6,12],"haR":[-105.7,70],"shL":[60.1,-121.4],"elL":[29.1,-41.4],"haL":[-33.1,-21.5],"hipR":[-12.5,35.6],"knR":[47.6,153.1],"ftR":[65,305.4],"hipL":[34.1,33.6],"knL":[17.4,174.7],"ftL":[-44.7,295.5]},{"rootY":22.5,"hips":[0,0],"chest":[0,-87.6],"neck":[0,-87.6],"head":[-7.6,-152.6],"shR":[-62.3,-99.4],"elR":[-79.9,10.8],"haR":[-121.2,63.7],"shL":[60.1,-119.9],"elL":[42,-38.6],"haL":[-13,-14],"hipR":[-11.7,35.4],"knR":[49.7,151.8],"ftR":[65.1,304],"hipL":[34.6,33.2],"knL":[17.8,174.4],"ftL":[-44.1,294.9]},{"rootY":22.8,"hips":[0,0],"chest":[-0.3,-87.5],"neck":[-0.3,-87.5],"head":[-6.3,-152.6],"shR":[-63.1,-100.5],"elR":[-88.3,9.4],"haR":[-133.2,56.4],"shL":[59.9,-119],"elL":[52.6,-35.4],"haL":[11.5,-6.6],"hipR":[-11.4,34.7],"knR":[51.7,151],"ftR":[65.9,303.1],"hipL":[34.3,33.6],"knL":[19.6,175],"ftL":[-42.7,294.9]},{"rootY":22.9,"hips":[0,0],"chest":[-0.4,-87.6],"neck":[-0.4,-87.6],"head":[-4.6,-152.8],"shR":[-63.3,-101.8],"elR":[-95.3,7],"haR":[-141.3,46.8],"shL":[60,-117.7],"elL":[61.1,-32.5],"haL":[40.8,-0.3],"hipR":[-10.3,34.7],"knR":[54.5,150.7],"ftR":[67.9,303],"hipL":[34.7,33.4],"knL":[22.3,175],"ftL":[-39.9,294.9]},{"rootY":21.9,"hips":[0,0],"chest":[-0.7,-87.6],"neck":[-0.7,-87.6],"head":[-3.3,-152.9],"shR":[-63.7,-103.4],"elR":[-101.9,3.6],"haR":[-147.1,35.8],"shL":[59.8,-116.3],"elL":[69.5,-30.5],"haL":[71.1,1.9],"hipR":[-9.3,34.8],"knR":[56.4,151.5],"ftR":[69.9,304.1],"hipL":[35,33.3],"knL":[24.4,175],"ftL":[-37.4,296]},{"rootY":20.5,"hips":[0,0],"chest":[-0.6,-87.6],"neck":[-0.6,-87.6],"head":[-1.6,-152.9],"shR":[-63.6,-104.2],"elR":[-108.1,0.3],"haR":[-150.2,25],"shL":[59.4,-115.3],"elL":[80.6,-29.8],"haL":[101.2,1.3],"hipR":[-9,34.9],"knR":[57,152.8],"ftR":[72.8,305.5],"hipL":[34.9,33.5],"knL":[25.9,175.5],"ftL":[-34.5,298.4]},{"rootY":19.3,"hips":[0,0],"chest":[-0.2,-87.7],"neck":[-0.2,-87.7],"head":[0.1,-152.9],"shR":[-62.9,-105.6],"elR":[-113.1,-3.7],"haR":[-150.2,14.5],"shL":[59.3,-114.3],"elL":[93.5,-30.6],"haL":[130.6,-2.3],"hipR":[-8.7,35.4],"knR":[56.8,154],"ftR":[75.5,306.5],"hipL":[35,33.5],"knL":[26.2,175.7],"ftL":[-31.4,300.6]},{"rootY":17.9,"hips":[0,0],"chest":[0.4,-87.7],"neck":[0.4,-87.7],"head":[2,-152.9],"shR":[-62,-106.6],"elR":[-116.6,-7.1],"haR":[-149.3,5.6],"shL":[59.3,-113.5],"elL":[107.1,-31],"haL":[155,-6.9],"hipR":[-8.6,36],"knR":[55.3,155],"ftR":[77.2,307.3],"hipL":[35.1,33.5],"knL":[25.8,175.7],"ftL":[-28.5,303.3]},{"rootY":16.8,"hips":[0,0],"chest":[1.6,-87.7],"neck":[1.6,-87.7],"head":[4.3,-152.8],"shR":[-60.4,-107.6],"elR":[-118.4,-10.2],"haR":[-147,-1.6],"shL":[60,-112.8],"elL":[120.1,-32.5],"haL":[175.9,-11],"hipR":[-9.4,36.5],"knR":[53.3,155.3],"ftR":[77.9,307.4],"hipL":[34.8,33.7],"knL":[25.5,176.2],"ftL":[-25.1,306.4]},{"rootY":16.1,"hips":[0,0],"chest":[3,-87.7],"neck":[3,-87.7],"head":[6.9,-152.6],"shR":[-58.4,-108.6],"elR":[-118.6,-13],"haR":[-143.5,-6.9],"shL":[61.3,-111.9],"elL":[129.8,-34.1],"haL":[190.2,-14.6],"hipR":[-10.2,36.8],"knR":[50.2,155.7],"ftR":[75.6,307.8],"hipL":[34.6,33.9],"knL":[25.5,176.6],"ftL":[-21.9,308.9]},{"rootY":15.9,"hips":[0,0],"chest":[4.4,-87.6],"neck":[4.4,-87.6],"head":[9.3,-152.4],"shR":[-56.4,-109.5],"elR":[-117.7,-15],"haR":[-139.8,-10],"shL":[62.7,-111.4],"elL":[135,-36.4],"haL":[198.3,-18.2],"hipR":[-11,37.2],"knR":[46.6,155.7],"ftR":[70.5,308],"hipL":[34.4,34.2],"knL":[25,176.9],"ftL":[-19,311]},{"rootY":15.1,"hips":[0,0],"chest":[5.6,-87.5],"neck":[5.6,-87.5],"head":[11.7,-151.9],"shR":[-54.8,-109.9],"elR":[-116.2,-16.1],"haR":[-135.9,-10.5],"shL":[63.5,-111.1],"elL":[134.7,-38.4],"haL":[199.1,-21.3],"hipR":[-11.6,37.4],"knR":[42.7,155.5],"ftR":[60.9,308.5],"hipL":[34.1,34.4],"knL":[24.1,177.2],"ftL":[-16.7,312.7]}]}